celloapi2/__init__.py
celloapi2/celloapi.py
celloapi2-0.2.4.dist-info/WHEEL
celloapi2-0.2.4.dist-info/METADATA
celloapi2-0.2.4.dist-info/RECORD
