Metadata-Version: 2.1
Name: celloapi2
Version: 0.2.4
Summary: 
Author: W.R. Jackson
Author-email: jackson@justjackson.dev
Requires-Python: >=3.8,<4.0
Classifier: Programming Language :: Python :: 3
Classifier: Programming Language :: Python :: 3.8
Classifier: Programming Language :: Python :: 3.9
Requires-Dist: PyYAML (>=5.4.1,<6.0.0)
Requires-Dist: numpy (>=1.20.1,<2.0.0)
